nathan_picsou/__init__.py
nathan_picsou/picsou.py
nathan_picsou-0.1.0.dist-info/METADATA
nathan_picsou-0.1.0.dist-info/WHEEL
nathan_picsou-0.1.0.dist-info/RECORD
